pyarmeetup2020/__init__.py
pyarmeetup2020/example.py
pyarmeetup2020-0.4.dist-info/LICENSE
pyarmeetup2020-0.4.dist-info/WHEEL
pyarmeetup2020-0.4.dist-info/METADATA
pyarmeetup2020-0.4.dist-info/RECORD
