Metadata-Version: 2.1
Name: pyarmeetup2020
Version: 0.4
Summary: My sample module
Author-email: Ambro17 <ambro17.1@gmail.com>
Classifier: License :: OSI Approved :: GNU General Public License v3 or later (GPLv3+)
Requires-Dist: Flask >= 2.0.2
Requires-Dist: elpasado == 0.0.7
